stacker/__init__.py
stacker/core.py
stacker/errors.py
stacker/lang.py
stacker/repl.py
stacker/scope.py
stacker_lang-0.4.0.dist-info/DESCRIPTION.rst
stacker_lang-0.4.0.dist-info/METADATA
stacker_lang-0.4.0.dist-info/RECORD
stacker_lang-0.4.0.dist-info/WHEEL
stacker_lang-0.4.0.dist-info/entry_points.txt
stacker_lang-0.4.0.dist-info/metadata.json
stacker_lang-0.4.0.dist-info/pbr.json
stacker_lang-0.4.0.dist-info/top_level.txt
