Metadata-Version: 2.0
Name: stacker-lang
Version: 0.4.0
Summary: A quick and dirty attempt at a stack oriented language
Home-page: https://github.com/djds23/stacker-lang
Author: Dean Silfen
Author-email: dean.silfen@gmail.com
License: MIT
Keywords: stacker lang programming language stack
Platform: UNKNOWN
Classifier: Development Status :: 3 - Alpha
Classifier: Intended Audience :: Developers
Classifier: Topic :: Software Development
Classifier: Topic :: Utilities
Classifier: License :: OSI Approved :: MIT License
Classifier: Programming Language :: Python :: 3
Classifier: Programming Language :: Python :: 3.3
Classifier: Programming Language :: Python :: 3.4
Classifier: Programming Language :: Python :: 3.5
Provides-Extra: dev
Requires-Dist: check-manifest; extra == 'dev'
Provides-Extra: test
Requires-Dist: coverage; extra == 'test'
